CyberChef/__init__.py
CyberChef/browser.py
CyberChef/scraper.py
Chaf-2.0.0.dist-info/LICENSE
Chaf-2.0.0.dist-info/METADATA
Chaf-2.0.0.dist-info/WHEEL
Chaf-2.0.0.dist-info/top_level.txt
Chaf-2.0.0.dist-info/RECORD
